pretix_signature_question/__init__.py
pretix_signature_question/apps.py
pretix_signature_question/signals.py
pretix_signature_question/locale/de/LC_MESSAGES/django.mo
pretix_signature_question/locale/de/LC_MESSAGES/django.po
pretix_signature_question/locale/de_Informal/.gitkeep
pretix_signature_question/locale/de_Informal/LC_MESSAGES/django.mo
pretix_signature_question/locale/de_Informal/LC_MESSAGES/django.po
pretix_signature_question/static/pretix_signature_question/.gitkeep
pretix_signature_question/static/pretix_signature_question/jSignature.min.js
pretix_signature_question/static/pretix_signature_question/main.js
pretix_signature_question/static/pretix_signature_question/main.min.js
pretix_signature_question/templates/pretix_signature_question/.gitkeep
pretix_signature_question/templates/pretix_signature_question/presale_head.html
pretix_signature_question_2-1.1.0.dist-info/LICENSE
pretix_signature_question_2-1.1.0.dist-info/METADATA
pretix_signature_question_2-1.1.0.dist-info/WHEEL
pretix_signature_question_2-1.1.0.dist-info/entry_points.txt
pretix_signature_question_2-1.1.0.dist-info/top_level.txt
pretix_signature_question_2-1.1.0.dist-info/RECORD
