Metadata-Version: 2.1
Name: pretix-signature-question-2
Version: 1.1.0
Summary: Allows to draw a signature
Author-email: pretix team <support@pretix.eu>
Maintainer-email: pretix team <support@pretix.eu>
License: 
Project-URL: homepage, https://github.com/pretix-unofficial/pretix-signature-question
Keywords: pretix
Requires-Python: >=3.9
License-File: LICENSE
